fusegrader/__init__.py
fusegrader/grader.py
fuse_grader-0.1.9.dist-info/METADATA
fuse_grader-0.1.9.dist-info/WHEEL
fuse_grader-0.1.9.dist-info/top_level.txt
fuse_grader-0.1.9.dist-info/RECORD
