Metadata-Version: 2.1
Name: fuse-grader
Version: 0.1.9
Summary: Assignment grader.
Home-page: UNKNOWN
Author: Anish Shrestha
Author-email: anishshrestha@fusemachines.com
License: UNKNOWN
Platform: UNKNOWN
Requires-Dist: requests (==2.25.0)
Requires-Dist: numpy (==1.19.3)
